muse/__init__.py
muse/ast_struct.py
muse/auto_complete.py
muse/data_interface.py
muse/error.py
muse/func_desc.py
muse/interpreter.py
muse/middata_sample.py
muse/muse_config.py
muse/muse_lang.py
muse/muse_test.py
muse/parser.py
muse/resolver.py
muse/sample.py
muse/scanner.py
muse/data/主体信息.xlsx
muse/data/主体指标.xlsx
muse/data/产品信息.xlsx
muse/data/产品指标.xlsx
muse/data/产品指标列.xlsx
muse/data/产品指标汇总.xlsx
muse/data/产品标签.xlsx
muse/data/产品标签列.xlsx
muse/data/持仓指标.xlsx
muse/data/资产信息.xlsx
muse/data/资产指标.xlsx
muse/data/资产指标列.xlsx
muse/data/资产指标汇总.xlsx
muse/data/资产标签.xlsx
muse/data/资产标签列.xlsx
muse/data/指标库/rep.json
muse/data/指标库/产品估值.xlsx
muse/data/指标库/产品大类资产占比.xlsx
muse/data/指标库/产品收益.xlsx
muse/data/指标库/产品要素.xlsx
muse/data/指标库/产品风险.xlsx
muse/data/指标库/持仓明细.xlsx
muse/data/指标库/资产要素.xlsx
muse/data_source/__init__.py
muse/data_source/base.py
muse/data_source/db_ds.py
muse/data_source/ds_manager.py
muse/data_source/ds_utils.py
muse/data_source/file_ds.py
muse/data_source/test_ds.py
muse/engines/__init__.py
muse/engines/algo_engine.py
muse/engines/calc_engine.py
muse/engines/indicator_engine.py
muse/engines/rule_engine.py
muse/engines/tag_engine.py
muse/utils/__init__.py
muse/utils/code_utils.py
muse/utils/jx_http_request.py
muse_lang-0.6.3.dist-info/METADATA
muse_lang-0.6.3.dist-info/WHEEL
muse_lang-0.6.3.dist-info/top_level.txt
muse_lang-0.6.3.dist-info/RECORD
