Metadata-Version: 2.4
Name: muse_lang
Version: 0.6.3
Summary: Mini language for data analysis of asset management.
Home-page: https://e.coding.net/brookslu/muse/muse.git
Author: Brooks Lu
Author-email: lxc@jixunet.com
Classifier: Programming Language :: Python :: 3
Classifier: License :: OSI Approved :: MIT License
Classifier: Operating System :: OS Independent
Requires-Python: >=3.8
Requires-Dist: numpy>=1.24.4
Requires-Dist: pandas>=2.0.3
Requires-Dist: polars>=1.8.0
Requires-Dist: fastexcel>=0.12.0
Dynamic: author
Dynamic: author-email
Dynamic: classifier
Dynamic: description
Dynamic: description-content-type
Dynamic: home-page
Dynamic: requires-dist
Dynamic: requires-python
Dynamic: summary
